heatmaps_to_keypoints.cpython-311-aarch64-linux-gnu.so
heatmaps_to_keypoints-0.0.3.dist-info/licenses/LICENSE.txt
heatmaps_to_keypoints-0.0.3.dist-info/METADATA
heatmaps_to_keypoints-0.0.3.dist-info/WHEEL
heatmaps_to_keypoints-0.0.3.dist-info/top_level.txt
heatmaps_to_keypoints-0.0.3.dist-info/RECORD
