Metadata-Version: 2.4
Name: heatmaps_to_keypoints
Version: 0.0.3
Summary: Fast C++ heatmap-to-keypoints decoder for pose estimation
Author: Clinton Mwangi
License: MIT License
Classifier: Programming Language :: Python :: 3
Classifier: Programming Language :: C++
Classifier: Operating System :: POSIX :: Linux
Requires-Python: >=3.9
License-File: LICENSE.txt
Requires-Dist: torch
Dynamic: license-file
